Workbook

Sheet Raw Data 2024
A2: Income Statement (Standard (5FY + TTM))
A3: Downloaded On: 26-Nov-2025
A4: Company: Top Glove (KLS: 7113) | B4: FY 2024 | C4: FY 2025 | D4: Aug-2025
A6: Amounts in Thousands, MYR (except Ratios, Multiples & per share items)
B8: Filed: 09-Oct-2025 | C8: Filed: 09-Oct-2025 | D8: Filed: 09-Oct-2025
B9: FY 2024
A10: Gross Profit
A11: Revenue | B11: 2514408
A12: Cost of Revenue | B12: -2249085
A13: Total Gross Profit | B13: =B11+B12 -> 265323
A14: Distribution and Selling Costs | B14: -76190
A15: Administrative and General Expenses | B15: -379686
A16: Other income | B16: =164870+1722 -> 166592
A17: EBITDA | B17: =SUM(B13:B16) -> -23961
A18: Impairment losses on goodwill, property, plant and equipment and right-of-use assets | B18: 0
A19: Property, plant and equipment written off (Depreciation) | B19: -10212
A20: EBIT | B20: =SUM(B17:B19) -> -34173
A21: Interest Expense | B21: -9941
A22: Interest income | B22: 12773
A23: PBT | B23: =SUM(B20:B22) -> -31341
A24: Tax (Expense)/ Credit | B24: 9929
A25: PAT | B25: =SUM(B23:B24) -> -21412
A27: BALANCE SHEET
A29: Assets
A30: Current Assets
A31: Cash, Cash Equivalents and Short Term Investments
A32: Cash and Cash Equivalents
A33: Cash | B33: 282839
A34: Cash Equivalents
A35: Total Cash and Cash Equivalents | B35: 282839
A36: Short Term Investments
A37: Available-for-Sale Securities, Current | B37: 32213
A38: Other Short Term Investments | B38: 618173
A39: Total Short Term Investments | B39: 650386
A40: Total Cash, Cash Equivalents and Short Term Investments | B40: 933225
A41: Cash Restricted or Pledged, Current | B41: 68348
A42: Derivative Investment and Hedging Assets, Current | B42: 245
A43: Inventories
A44: Raw Materials, Consumables and Supplies | B44: 97528
A45: Work-in-Process | B45: 63442
A46: Finished Goods and Merchandise | B46: 215328
A47: Total Inventories | B47: 376298
A48: Trade and Other Receivables, Current
A49: Trade/Accounts Receivable, Current
A50: Gross Trade/Accounts Receivable, Current | B50: 344759
A51: Allowance/Adjustments for Trade/Accounts Receivable, Current | B51: -3577
A52: Total Trade/Accounts Receivable, Current | B52: 341182
A53: Taxes Receivable, Current | B53: 28346
A54: Other Receivables, Current | B54: 16066
A55: Total Trade and Other Receivables, Current | B55: 385594
A56: Prepayments and Deposits, Current | B56: 56180
A57: Assets Held for Sale/Discontinued Operations, Current | B57: 11517
A58: Other Current Assets
A59: Total Current Assets | B59: 1831407
A60: Non-Current Assets
A61: Net Property, Plant and Equipment
A62: Gross Property, Plant and Equipment
A63: Properties
A64: Land and Improvements | B64: 707590
A65: Buildings and Improvements | B65: 918280
A66: Total Properties | B66: 1625870
A67: Machinery, Furniture and Equipment
A68: Plant and Machinery | B68: 2596675
A69: Total Machinery, Furniture and Equipment | B69: 2596675
A70: Construction in Progress and Advance Payments | B70: 997442
A71: Leased Property, Plant and Equipment | B71: 11499
A72: Other Property, Plant and Equipment | B72: 369822
A73: Total Gross Property, Plant and Equipment | B73: 5601308
A74: Accumulated Depreciation and Impairment
A75: Accumulated Depreciation
A76: Accumulated Depreciation of Properties
A77: Accumulated Depreciation of Land and Improvements | B77: 0
A78: Accumulated Depreciation of Buildings | B78: -150667
A79: Total Accumulated Depreciation of Properties | B79: -150667
A80: Accumulated Depreciation of Machinery, Furniture and Equipment
A81: Accumulated Depreciation of Plant and Machinery | B81: -1376157
A82: Total Accumulated Depreciation of Machinery, Furniture and Equipment | B82: -1376157
A83: Accumulated Depreciation of Construction in Progress | B83: 0
A84: Accumulated Depreciation of Other Property, Plant and Equipment | B84: -243404
A85: Total Accumulated Depreciation | B85: -1770228
A86: Accumulated Impairment of PPE | B86: -52224
A87: Total Accumulated Depreciation and Impairment | B87: -1822452
A88: Total Net Property, Plant and Equipment | B88: 3778856
A89: Investment Properties and Properties Held for Development | B89: 468316
A90: Net Intangible Assets
A91: Gross Goodwill and Other Intangible Assets
A92: Goodwill | B92: 980691
A93: Intangibles other than Goodwill
A94: Trademarks and Patents | B94: 1460
A95: Customer Relationships | B95: 40477
A96: Total Intangibles other than Goodwill | B96: 41937
A97: Total Gross Goodwill and Other Intangible Assets | B97: 1022628
A98: Accumulated Amortization and Impairment
A99: Accumulated Amortization of Intangible Assets
A100: Accumulated Amortization of Intangibles other than Goodwill
A101: Accumulated Amortization of Trademarks and Patents | B101: -280
A102: Accumulated Amortization of Customer Relationships | B102: -23613
A103: Total Accumulated Amortization of Intangibles other than Goodwill | B103: -23893
A104: Total Accumulated Amortization of Intangible Assets | B104: -23893
A105: Accumulated Impairment of Intangible Assets
...

Sheet Model
B2: 3-STATEMENT FINANCIAL MODEL
B3: Top Glove Corporation (Amounts in Thousands, MYR)
B5: ASSUMPTIONS
C7: Base Year | D7: Year 1 | E7: Year 2 | F7: Year 3 | G7: Year 4 | H7: Year 5
C8: FY 2024 | D8: FY 2025 | E8: FY 2026 | F8: FY 2027 | G8: FY 2028 | H8: FY 2029
B10: Revenue Growth Rate | D10: 0.15 | E10: 0.15 | F10: 0.1 | G10: 0.1 | H10: 0.05
B11: Gross Profit Margin | D11: 0.15 | E11: 0.15 | F11: 0.15 | G11: 0.15 | H11: 0.15
B12: EBITDA Margin | D12: 0.1 | E12: 0.1 | F12: 0.1 | G12: 0.15 | H12: 0.15
B14: Existing PPE (Base) | C14: 3778856
B15: Existing PPE Useful Life (years) | C15: 5
B16: Existing PPE Annual Depreciation | C16: =C14/C15 -> 755771.2
B18: Replacement Capex (% of Revenue) | D18: 0.05 | E18: 0.05 | F18: 0.05 | G18: 0.05 | H18: 0.05
B19: New Capex Useful Life (years) | C19: 5
B21: Tax Rate | D21: 0.2 | E21: 0.2 | F21: 0.2 | G21: 0.2 | H21: 0.2
B23: Inventory Turnover Days | C23: 30
B24: Receivable Turnover Days | C24: 30
B25: Payable Turnover Days | C25: 60
B27: Opening Debt (Total) | C27: 422092
B28: Interest Rate on Debt | C28: 0.07
B29: Minimum Cash Balance | C29: 100000
B32: INCOME STATEMENT | C32: FY 2024 | D32: FY 2025 | E32: FY 2026 | F32: FY 2027 | G32: FY 2028 | H32: FY 2029
B34: Revenue | C34: 2514408 | D34: =C34*(1+D10) -> 2891569.2 | E34: =D34*(1+E10) -> 3325304.6 | F34: =E34*(1+F10) -> 3657835 | G34: =F34*(1+G10) -> 4023618.5 | H34: =G34*(1+H10) -> 4224799.5
B35: Cost of Revenue | C35: -2249085 | D35: =-D34*(1-D11) -> -2457833.8 | E35: =-E34*(1-E11) -> -2826508.9 | F35: =-F34*(1-F11) -> -3109159.8 | G35: =-G34*(1-G11) -> -3420075.8 | H35: =-H34*(1-H11) -> -3591079.5
B36: Gross Profit | C36: =C34+C35 -> 265323 | D36: =D34+D35 -> 433735.38 | E36: =E34+E35 -> 498795.69 | F36: =F34+F35 -> 548675.26 | G36: =G34+G35 -> 603542.78 | H36: =H34+H35 -> 633719.92
B38: EBITDA | C38: -23961 | D38: =D34*D12 -> 289156.92 | E38: =E34*E12 -> 332530.46 | F38: =F34*F12 -> 365783.5 | G38: =G34*G12 -> 603542.78 | H38: =H34*H12 -> 633719.92
B39: Depreciation & Amortization | C39: -10212 | D39: =-$C$16 -> -755771.2 | E39: =-$C$16-(D34*D18)/$C$19 -> -784686.89 | F39: =-$C$16-(D34*D18)/$C$19-(E34*E18)/$C$19 -> -817939.94 | G39: =-$C$16-(D34*D18)/$C$19-(E34*E18)/$C$19-(F34*F18)/$C$19 -> -854518.29 | H39: =-$C$16-(D34*D18)/$C$19-(E34*E18)/$C$19-(F34*F18)/$C$19-(G34*G18)/$C$19 -> -894754.47
B40: EBIT | C40: =C38+C39 -> -34173 | D40: =D38+D39 -> -466614.28 | E40: =E38+E39 -> -452156.43 | F40: =F38+F39 -> -452156.43 | G40: =G38+G39 -> -250975.51 | H40: =H38+H39 -> -261034.55
B41: Interest Expense | C41: -9941 | D41: =-$C$28*C27 -> -29546.44 | E41: =-$C$28*D68 -> 0 | F41: =-$C$28*E68 -> 0 | G41: =-$C$28*F68 -> 0 | H41: =-$C$28*G68 -> 0
B42: Interest Income | C42: 12773 | D42: 12773 | E42: 12773 | F42: 12773 | G42: 12773 | H42: 12773
B43: Profit Before Tax (PBT) | C43: =C40+C41+C42 -> -31341 | D43: =D40+D41+D42 -> -483387.72 | E43: =E40+E41+E42 -> -439383.43 | F43: =F40+F41+F42 -> -439383.43 | G43: =G40+G41+G42 -> -238202.51 | H43: =H40+H41+H42 -> -248261.55
B44: Tax Expense | C44: 9929 | D44: =-MAX(0,D43)*D21 -> 0 | E44: =-MAX(0,E43)*E21 -> 0 | F44: =-MAX(0,F43)*F21 -> 0 | G44: =-MAX(0,G43)*G21 -> 0 | H44: =-MAX(0,H43)*H21 -> 0
B45: Net Income (PAT) | C45: =C43+C44 -> -21412 | D45: =D43+D44 -> -483387.72 | E45: =E43+E44 -> -439383.43 | F45: =F43+F44 -> -439383.43 | G45: =G43+G44 -> -238202.51 | H45: =H43+H44 -> -248261.55
B48: BALANCE SHEET | C48: FY 2024 | D48: FY 2025 | E48: FY 2026 | F48: FY 2027 | G48: FY 2028 | H48: FY 2029
B50: ASSETS
B51: Cash & Cash Equivalents | C51: 933225 | D51: {=D110} -> 1126188.5 | E51: {=E110} -> 1299879.3 | F51: {=F110} -> 1491444.4 | G51: {=G110} -> 1902069.6 | H51: {=H110} -> 2334842.2
B52: Accounts Receivable | C52: 341182 | D52: =D34*($C$24/365) -> 237663.22 | E52: =E34*($C$24/365) -> 273312.71 | F52: =F34*($C$24/365) -> 300643.98 | G52: =G34*($C$24/365) -> 330708.37 | H52: =H34*($C$24/365) -> 347243.79
B53: Inventory | C53: 376298 | D53: =-D35*($C$23/365) -> 202013.74 | E53: =-E35*($C$23/365) -> 232315.8 | F53: =-F35*($C$23/365) -> 255547.38 | G53: =-G35*($C$23/365) -> 281102.12 | H53: =-H35*($C$23/365) -> 295157.22
B54: Total Current Assets | C54: =SUM(C51:C53) -> 1650705 | D54: =SUM(D51:D53) -> 1565865.5 | E54: =SUM(E51:E53) -> 1805507.8 | F54: =SUM(F51:F53) -> 2047635.8 | G54: =SUM(G51:G53) -> 2513880.1 | H54: =SUM(H51:H53) -> 2977243.2
B56: Net PP&E | C56: 3778856 | D56: =C56+D39+(D34*D18) -> 3167663.3 | E56: =D56+E39+(E34*E18) -> 2549241.6 | F56: =E56+F39+(F34*F18) -> 1914193.4 | G56: =F56+G39+(G34*G18) -> 1260856.1 | H56: =G56+H39+(H34*H18) -> 577341.55
B57: Other Non-Current Assets | C57: 1347830 | D57: {=C57} -> 1347830 | E57: {=D57} -> 1347830 | F57: {=E57} -> 1347830 | G57: {=F57} -> 1347830 | H57: {=G57} -> 1347830
B58: Total Non-Current Assets | C58: =C56+C57 -> 5126686 | D58: =D56+D57 -> 4515493.3 | E58: =E56+E57 -> 3897071.6 | F58: =F56+F57 -> 3262023.4 | G58: =G56+G57 -> 2608686.1 | H58: =H56+H57 -> 1925171.5
B60: TOTAL ASSETS | C60: =C54+C58 -> 6777391 | D60: =D54+D58 -> 6081358.8 | E60: =E54+E58 -> 5702579.4 | F60: =F54+F58 -> 5309659.2 | G60: =G54+G58 -> 5122566.1 | H60: =H54+H58 -> 4902414.8
B63: LIABILITIES
B64: Accounts Payable | C64: 194580 | D64: =-D35*($C$25/365) -> 404027.48 | E64: =-E35*($C$25/365) -> 464631.6 | F64: =-F35*($C$25/365) -> 511094.76 | G64: =-G35*($C$25/365) -> 562204.23 | H64: =-H35*($C$25/365) -> 590314.45
B65: Other Current Liabilities | C65: 755223 | D65: {=C65} -> 755223 | E65: {=D65} -> 755223 | F65: {=E65} -> 755223 | G65: {=F65} -> 755223 | H65: {=G65} -> 755223
B66: Total Current Liabilities | C66: =C64+C65 -> 949803 | D66: =D64+D65 -> 1159250.5 | E66: =E64+E65 -> 1219854.6 | F66: =F64+F65 -> 1266317.8 | G66: =G64+G65 -> 1317427.2 | H66: =H64+H65 -> 1345537.4
B68: Total Debt | C68: 422092 | D68: =MAX(0,C68+D103) -> 0 | E68: =MAX(0,D68+E103) -> 0 | F68: =MAX(0,E68+F103) -> 0 | G68: =MAX(0,F68+G103) -> 0 | H68: =MAX(0,G68+H103) -> 0
B69: Other Non-Current Liabilities | C69: 150702 | D69: {=C69} -> 150702 | E69: {=D69} -> 150702 | F69: {=E69} -> 150702 | G69: {=F69} -> 150702 | H69: {=G69} -> 150702
B70: Total Non-Current Liabilities | C70: =C68+C69 -> 572794 | D70: =D68+D69 -> 150702 | E70: =E68+E69 -> 150702 | F70: =F68+F69 -> 150702 | G70: =G68+G69 -> 150702 | H70: =H68+H69 -> 150702
B72: TOTAL LIABILITIES | C72: =C66+C70 -> 1522597 | D72: =D66+D70 -> 1309952.5 | E72: =E66+E70 -> 1370556.6 | F72: =F66+F70 -> 1417019.8 | G72: =G66+G70 -> 1468129.2 | H72: =H66+H70 -> 1496239.4
B75: EQUITY
B76: Share Capital & Reserves | C76: 5276206 | D76: {=C76} -> 5276206 | E76: {=D76} -> 5276206 | F76: {=E76} -> 5276206 | G76: {=F76} -> 5276206 | H76: {=G76} -> 5276206
B77: Retained Earnings | C77: -21412 | D77: =C77+D45 -> -504799.72 | E77: =D77+E45 -> -944183.15 | F77: =E77+F45 -> -1383566.6 | G77: =F77+G45 -> -1621769.1 | H77: =G77+H45 -> -1870030.6
B78: TOTAL EQUITY | C78: =C76+C77 -> 5254794 | D78: =D76+D77 -> 4771406.3 | E78: =E76+E77 -> 4332022.8 | F78: =F76+F77 -> 3892639.4 | G78: =G76+G77 -> 3654436.9 | H78: =H76+H77 -> 3406175.4
B80: TOTAL LIABILITIES + EQUITY | C80: =C72+C78 -> 6777391 | D80: =D72+D78 -> 6081358.8 | E80: =E72+E78 -> 5702579.4 | F80: =F72+F78 -> 5309659.2 | G80: =G72+G78 -> 5122566.1 | H80: =H72+H78 -> 4902414.8
B82: Balance Check (Assets - Liabilities - Equity) | D82: =D60-D72-D78 -> 0 | E82: =E60-E72-E78 -> 0 | F82: =F60-F72-F78 -> 0 | G82: =G60-G72-G78 -> 0 | H82: =H60-H72-H78 -> 0
B83: CASH FLOW STATEMENT
B85: Cash Flow from Operations (CFO) | C85: FY 2024 | D85: FY 2025 | E85: FY 2026 | F85: FY 2027 | G85: FY 2028 | H85: FY 2029
B86: Net Income | D86: {=D45} -> -483387.72 | E86: {=E45} -> -439383.43 | F86: {=F45} -> -439383.43 | G86: {=G45} -> -238202.51 | H86: {=H45} -> -248261.55
B87: (+) Depreciation & Amortization | D87: =-D39 -> 755771.2 | E87: =-E39 -> 784686.89 | F87: =-F39 -> 817939.94 | G87: =-G39 -> 854518.29 | H87: =-H39 -> 894754.47
B88: Changes in Working Capital:
B89: (-) Change in Receivables | D89: =-(D52-C52) -> 103518.78 | E89: =-(E52-D52) -> -35649.483 | F89: =-(F52-E52) -> -27331.271 | G89: =-(G52-F52) -> -30064.398 | H89: =-(H52-G52) -> -16535.419
B90: (-) Change in Inventory | D90: =-(D53-C53) -> 174284.26 | E90: =-(E53-D53) -> -30302.061 | F90: =-(F53-E53) -> -23231.58 | G90: =-(G53-F53) -> -25554.738 | H90: =-(H53-G53) -> -14055.106
B91: (+) Change in Payables | D91: =D64-C64 -> 209447.48 | E91: =E64-D64 -> 60604.122 | F91: =F64-E64 -> 46463.16 | G91: =G64-F64 -> 51109.476 | H91: =H64-G64 -> 28110.212
B93: Net Cash from Operations | D93: =SUM(D86:D87,D89:D91) -> 759634 | E93: =SUM(E86:E87,E89:E91) -> 339956.04 | F93: =SUM(F86:F87,F89:F91) -> 374456.81 | G93: =SUM(G86:G87,G89:G91) -> 611806.12 | H93: =SUM(H86:H87,H89:H91) -> 644012.61
B96: Cash Flow from Investing (CFI)
B97: (-) Capital Expenditure | D97: =-D34*D18 -> -144578.46 | E97: =-E34*E18 -> -166265.23 | F97: =-F34*F18 -> -182891.75 | G97: =-G34*G18 -> -201180.93 | H97: =-H34*H18 -> -211239.97
B99: Net Cash from Investing | D99: {=D97} -> -144578.46 | E99: {=E97} -> -166265.23 | F99: {=F97} -> -182891.75 | G99: {=G97} -> -201180.93 | H99: {=H97} -> -211239.97
B102: Cash Flow from Financing (CFF)
B103: (-) Debt Repayment | D103: =-MIN(C68,MAX(0,C51+D93+D99-$C$29)) -> -422092 | E103: =-MIN(D68,MAX(0,D51+E93+E99-$C$29)) -> 0 | F103: =-MIN(E68,MAX(0,E51+F93+F99-$C$29)) -> 0 | G103: =-MIN(F68,MAX(0,F51+G93+G99-$C$29)) -> 0 | H103: =-MIN(G68,MAX(0,G51+H93+H99-$C$29)) -> 0
B105: Net Cash from Financing | D105: {=D103} -> -422092 | E105: {=E103} -> 0 | F105: {=F103} -> 0 | G105: {=G103} -> 0 | H105: {=H103} -> 0
B108: Net Change in Cash | D108: =D93+D99+D105 -> 192963.54 | E108: =E93+E99+E105 -> 173690.81 | F108: =F93+F99+F105 -> 191565.06 | G108: =G93+G99+G105 -> 410625.19 | H108: =H93+H99+H105 -> 432772.63
B109: Beginning Cash Balance | D109: {=C51} -> 933225 | E109: {=D110} -> 1126188.5 | F109: {=E110} -> 1299879.3 | G109: {=F110} -> 1491444.4 | H109: {=G110} -> 1902069.6
B110: Ending Cash Balance | D110: =D109+D108 -> 1126188.5 | E110: =E109+E108 -> 1299879.3 | F110: =F109+F108 -> 1491444.4 | G110: =G109+G108 -> 1902069.6 | H110: =H109+H108 -> 2334842.2

Sheet DCF Valuation
B2: DCF VALUATION - INCOME APPROACH
B3: Top Glove Corporation (Amounts in Thousands, MYR)
B5: VALUATION ASSUMPTIONS
B7: Weighted Average Cost of Capital (WACC) | C7: 0.15
B8: Terminal Growth Rate | C8: 0.025 | D8: assuming growth stabilises after year 5 at 2.5%
B9: Tax Rate | C9: {=Model!D21} -> 0.2
B12: FREE CASH FLOW CALCULATION
C14: Year 1 | D14: Year 2 | E14: Year 3 | F14: Year 4 | G14: Year 5
C15: FY 2025 | D15: FY 2026 | E15: FY 2027 | F15: FY 2028 | G15: FY 2029
B17: EBIT | C17: {=Model!D40} -> -466614.28 | D17: {=Model!E40} -> -452156.43 | E17: {=Model!F40} -> -452156.43 | F17: {=Model!G40} -> -250975.51 | G17: {=Model!H40} -> -261034.55
B18: (-) Taxes on EBIT | C18: =-MAX(0,C17)*$C$9 -> 0 | D18: =-MAX(0,D17)*$C$9 -> 0 | E18: =-MAX(0,E17)*$C$9 -> 0 | F18: =-MAX(0,F17)*$C$9 -> 0 | G18: =-MAX(0,G17)*$C$9 -> 0
B19: NOPAT (EBIT after Tax) | C19: =C17+C18 -> -466614.28 | D19: =D17+D18 -> -452156.43 | E19: =E17+E18 -> -452156.43 | F19: =F17+F18 -> -250975.51 | G19: =G17+G18 -> -261034.55
B21: (+) Depreciation & Amortization | C21: =-Model!D39 -> 755771.2 | D21: =-Model!E39 -> 784686.89 | E21: =-Model!F39 -> 817939.94 | F21: =-Model!G39 -> 854518.29 | G21: =-Model!H39 -> 894754.47
B22: (-) Capital Expenditure | C22: {=Model!D97} -> -144578.46 | D22: {=Model!E97} -> -166265.23 | E22: {=Model!F97} -> -182891.75 | F22: {=Model!G97} -> -201180.93 | G22: {=Model!H97} -> -211239.97
B23: (+/-) Change in Working Capital | C23: =Model!D89+Model!D90+Model!D91 -> 487250.52 | D23: =Model!E89+Model!E90+Model!E91 -> -5347.4225 | E23: =Model!F89+Model!F90+Model!F91 -> -4099.6906 | F23: =Model!G89+Model!G90+Model!G91 -> -4509.6596 | G23: =Model!H89+Model!H90+Model!H91 -> -2480.3128
B25: Free Cash Flow to Firm (FCFF) | C25: =C19+C21+C22+C23 -> 631828.98 | D25: =D19+D21+D22+D23 -> 160917.81 | E25: =E19+E21+E22+E23 -> 178792.06 | F25: =F19+F21+F22+F23 -> 397852.19 | G25: =G19+G21+G22+G23 -> 419999.63
B28: DCF VALUATION
B30: Discount Period | C30: 1 | D30: 2 | E30: 3 | F30: 4 | G30: 5
B31: Discount Factor | C31: =1/(1+$C$7)^C30 -> 0.86956522 | D31: =1/(1+$C$7)^D30 -> 0.75614367 | E31: =1/(1+$C$7)^E30 -> 0.65751623 | F31: =1/(1+$C$7)^F30 -> 0.57175325 | G31: =1/(1+$C$7)^G30 -> 0.49717674
B32: PV of FCFF | C32: =C25*C31 -> 549416.5 | D32: =D25*D31 -> 121676.98 | E32: =E25*E31 -> 117558.68 | F32: =F25*F31 -> 227473.28 | G32: =G25*G31 -> 208814.05
B34: Sum of PV of Projected FCFF | C34: =SUM(C32:G32) -> 1224939.5
B37: TERMINAL VALUE (Gordon Growth Model)
B39: Terminal Year FCF (Year 5) | C39: {=G25} -> 419999.63
B40: Terminal Value | C40: =C39*(1+$C$8)/($C$7-$C$8) -> 3443997
B41: PV of Terminal Value | C41: =C40*G31 -> 1712275.2
B44: ENTERPRISE VALUE SUMMARY
B46: Sum of PV of Projected FCF (Years 1-5) | C46: {=C34} -> 1224939.5
B47: PV of Terminal Value | C47: {=C41} -> 1712275.2
B48: Enterprise Value (EV) | C48: =C46+C47 -> 2937214.7
B51: EQUITY VALUE BRIDGE
B53: Enterprise Value | C53: {=C48} -> 2937214.7
B54: (-) Total Debt | C54: =-Model!C68 -> -422092
B55: (+) Cash & Cash Equivalents in Base Year | C55: {=Model!C51} -> 933225
B57: Equity Value | C57: =C53+C54+C55 -> 3448347.7
B60: VALUATION METRICS
B62: % of EV from Terminal Value | C62: =C47/C48 -> 0.58295881
B63: % of EV from Projected FCF | C63: =C46/C48 -> 0.41704119
B65: Implied EV/Revenue (FY2029) | C65: =C48/Model!H34 -> 0.69523174
B66: Implied EV/EBITDA (FY2029) | C66: =C48/Model!H38 -> 4.6348783

Sheet Market-Comps
B2: MARKET APPROACH VALUATION
B3: Comparable Companies Analysis (Amounts in Thousands, MYR)
B5: COMPARABLE COMPANIES
B7: Company | C7: Ticker | D7: EV/EBITDA
B8: Hartalega Holdings | C8: KLS:5168 | D8: 12.12
B9: Kossan Rubber Industries | C9: KLS:7153 | D9: 5.82
B10: Riverstone Resources | C10: SES:AP4 | D10: 9.95
B11: SuperMax | C11: KLS:7106 | D11: N/A
B13: Median EV/EBITDA | D13: =MEDIAN(D8:D10) -> 9.95
B14: Mean EV/EBITDA | D14: =AVERAGE(D8:D10) -> 9.2966667
B16: Source: PitchBook (26-Nov-2025)
B19: MARKET APPROACH VALUATION
B21: EBITDA (FY2029 - Model) | C21: {=Model!H38} -> 633719.92
B22: Applied EV/EBITDA Multiple (Median) | C22: {=D13} -> 9.95
B24: Implied Enterprise Value | C24: =C21*C22 -> 6305513.2
B27: EQUITY VALUE BRIDGE
B29: Enterprise Value | C29: {=C24} -> 6305513.2
B30: (-) Total Debt | C30: =-Model!C68 -> -422092
B31: (+) Cash & Cash Equivalents | C31: {=Model!C51} -> 933225
B33: Equity Value | C33: =C29+C30+C31 -> 6816646.2
B36: COMPARISON WITH DCF VALUATION
B38: DCF Enterprise Value | C38: {='DCF Valuation'!C48} -> 2937214.7
B39: Market Comps Enterprise Value | C39: {=C24} -> 6305513.2
B40: Difference | C40: =C39-C38 -> 3368298.5
B41: % Difference | C41: =(C39-C38)/C38 -> 1.1467662
B42: *Difference is largely due to variation between WACC & median EV/EBITDA

Sheet Comparables
